HeimdallX/BaseMLClasses.py
HeimdallX/Config.py
HeimdallX/DataSetSynth.py
HeimdallX/ML_packaging.py
HeimdallX/RunTest.py
HeimdallX/TestSuite.py
HeimdallX/__init__.py
HeimdallX/_items.py
HeimdallX/pipeline.py
HeimdallX/yolo_class.py
heimdallx-0.3.dist-info/METADATA
heimdallx-0.3.dist-info/WHEEL
heimdallx-0.3.dist-info/licenses/LICENSE.md
heimdallx-0.3.dist-info/RECORD
