Metadata-Version: 2.3
Name: HeimdallX
Version: 0.3
Summary: A Machine Learning and Artificial Intelligence application package
Project-URL: Homepage, https://github.com/cjessop/ML_Task
Project-URL: Issues, https://github.com/cjessop/ML_Task/issues
Author-email: Christoher Jessop <chrisjessop123@gmail.com>
License-File: LICENSE.md
Classifier: License :: OSI Approved :: MIT License
Classifier: Operating System :: OS Independent
Classifier: Programming Language :: Python :: 3
Requires-Python: >=3.8
